{
  "type": "FeatureCollection",
  "features": [
    {
      "type": "Feature",
      "properties": {
        "nombre": "Colegio Torre del Castillo",
        "tipo": "Primaria",
        "incidencias": "Muro desplomado"
      },
      "geometry": {
        "type": "Point",
        "coordinates": [37,471867964	-4,582922212	360028,243248928	4148396,77296476]
      }
    },
    {
      "type": "Feature",
      "properties": {
        "nombre": "IES La Rosaleda",
        "tipo": "Secundaria",
        "incidencias": "Ninguna"
      },
      "geometry": {
        "type": "Point",
        "coordinates": [-4.42, 36.72]
      }
    },
    {
      "type": "Feature",
      "properties": {
        "nombre": "CEIP Andalucía",
        "tipo": "Infantil/Primaria",
        "incidencias": "Fotovoltaica defectuosa"
      },
      "geometry": {
        "type": "Point",
        "coordinates": [-5.98, 37.88]
      }
    }
  ]
}
